LICENSE
MANIFEST.in
README.md
runtests.py
setup.py
requirements/install.txt
requirements/tests.txt
wagtailtextanalysis/__init__.py
wagtailtextanalysis/apps.py
wagtailtextanalysis/signal_handlers.py
wagtailtextanalysis/text_analysis.py
wagtailtextanalysis.egg-info/PKG-INFO
wagtailtextanalysis.egg-info/SOURCES.txt
wagtailtextanalysis.egg-info/dependency_links.txt
wagtailtextanalysis.egg-info/not-zip-safe
wagtailtextanalysis.egg-info/requires.txt
wagtailtextanalysis.egg-info/top_level.txt
wagtailtextanalysis/providers/__init__.py
wagtailtextanalysis/providers/azure_text_analytics.py