Metadata-Version: 2.1
Name: wagtailtextanalysis
Version: 0.0.1
Summary: Detect key phrases and sentiment from your Wagtail content using cloud Api services
Home-page: https://github.com/marteinn/wagtail-text-analysis
Author: marteinn
Author-email: martin@marteinn.se
License: MIT
Platform: UNKNOWN
Classifier: Development Status :: 3 - Alpha
Classifier: Environment :: Web Environment
Classifier: Intended Audience :: Developers
Classifier: Natural Language :: English
Classifier: Intended Audience :: Developers
Classifier: License :: OSI Approved :: MIT License
Classifier: Programming Language :: Python
Classifier: Programming Language :: Python :: 3
Classifier: Programming Language :: Python :: 3.5
Classifier: Programming Language :: Python :: 3.6
Classifier: Topic :: Text Processing :: Linguistic
Classifier: Framework :: Wagtail :: 2
Classifier: Framework :: Django
Classifier: Topic :: Utilities
